{
  "version": 3,
  "middleware": {
    "/": {
      "files": [
        "server/edge/chunks/_a1b8b59d._.js",
        "server/edge/chunks/[root of the server]__04a9149b._.js",
        "server/edge/chunks/edge-wrapper_53a8b80c.js"
      ],
      "name": "middleware",
      "page": "/",
      "matchers": [
        {
          "regexp": "^\\/visaistic(?:\\/(_next\\/data\\/[^/]{1,}))?(?:\\/((?!api|_next|images|.well-known|favicon.ico|robots.txt|sitemap.xml).*))(\\\\.json)?[\\/#\\?]?$",
          "originalSource": "/((?!api|_next|images|.well-known|favicon.ico|robots.txt|sitemap.xml).*)"
        }
      ],
      "wasm": [],
      "assets": [],
      "env": {
        "__NEXT_BUILD_ID": "development",
        "NEXT_SERVER_ACTIONS_ENCRYPTION_KEY": "ESFjPbDpOZn0hHx18Xm9XBAhMIZm/KJ3dmZVgfWlX6g=",
        "__NEXT_PREVIEW_MODE_ID": "8816ba60b33e37ef4d3af37915044365",
        "__NEXT_PREVIEW_MODE_ENCRYPTION_KEY": "f1e841a5fbf7a798e9f2979c94cf2ec242ecf7710cddb82249fd4f67efae5040",
        "__NEXT_PREVIEW_MODE_SIGNING_KEY": "10a07b116a14e49e82ee56f73f63b6186fc79728e593c3604d7de495ce7c385a"
      }
    }
  },
  "sortedMiddleware": [
    "/"
  ],
  "functions": {}
}